{
  "fecha_inicio": "2025-05-12",
  "cancion_principal": "Virtual Love - Artist XYZ (nuestro himno de noches online)",
  "meses": [
    {"mes":1,"titulo":"El primer \"hola\" que cambió todo","cancion_dedicada":"Song 1 – Artist","momentos":["Primer DM eterno","Descubrir que los dos éramos nocturnos"],"foto":"img/minecraft.jpg"},
    {"mes":2,"titulo":"Llamadas hasta el amanecer","cancion_dedicada":"Song 2 – Artist","momentos":["5 horas hablando sin parar","Primera vez que dijiste \"te extraño\""],"foto":"img/valorant.jpg"},
    {"mes":3,"titulo":"Dúos legendarios","cancion_dedicada":"Song 3 – Artist","momentos":["Nuestra primera win en Valorant","Construimos una casa con corazón en Minecraft"],"foto":"img/forest.jpg"},
    {"mes":4,"titulo":"Secretos y risas 24/7","cancion_dedicada":"Song 4 – Artist","momentos":["Memes solo nuestros","Compartir playlists a las 3 a.m."],"foto":"img/party.jpg"},
    {"mes":5,"titulo":"Caos y amor en Roblox","cancion_dedicada":"Song 5 – Artist","momentos":["Adopt Me hasta las 5 am","Avatares a juego"],"foto":"img/roblox.jpg"},
    {"mes":6,"titulo":"Sobreviviendo monstruos y sentimientos","cancion_dedicada":"Song 6 – Artist","momentos":["The Forest y gritos de miedo","Apoyo mutuo en días difíciles"],"foto":"img/minecraft.jpg"},
    {"mes":7,"titulo":"7 meses y un amor sin distancia","cancion_dedicada":"Song 7 – Artist","momentos":["Planeando el primer meet real","Te quiero en todos los píxeles"],"foto":"img/valorant.jpg"}
  ],
  "juegos_top": [
    {"nombre":"Minecraft","portada":"img/minecraft.png","stats":"3 mundos, 1 corazón gigante y muchas granjas automáticas"},
    {"nombre":"Valorant","portada":"img/valorant.jpg","stats":"+40 wins juntos, 1 clutch histórico"},
    {"nombre":"The Forest","portada":"img/forest.jpg","stats":"10 noches sobrevividas (y muchos screams)"},
    {"nombre":"Party Games","portada":"img/party.jpg","stats":"Risas hasta llorar garantizadas"},
    {"nombre":"Roblox","portada":"img/roblox.jpg","stats":"20 mundos visitados, 1 solo nuestro"}
  ],
  "top_momentos": [
    "Construir un corazón gigante de obsidiana en Minecraft",
    "Clutch 1v4 en Valorant y gritarnos de emoción",
    "Sobrevivir la noche 100 en The Forest abrazados por voz",
    "Reír hasta llorar en Fall Guys / Among Us",
    "Nuestra primera foto de perfil a juego",
    "Cuando me dedicaste la canción 7 y lloré como bobo",
    "Todas las noches diciendo \"una última partida\" y eran 5 más"
  ]
}
